{
  "generated_at_utc": "2026-01-04T04:22:50.489820+00:00",
  "watch_count": 2,
  "warnings": [],
  "channels": [
    {
      "channel_id": "UCB9cirTse_-h02qZ6ctmBzw",
      "watch_key": "UCB9cirTse_-h02qZ6ctmBzw",
      "title": "trueman_project",
      "sticky_red_count": 8,
      "red_top_count": 7,
      "max_anomaly_ratio": 123.6719971223286
    },
    {
      "channel_id": "UCB9cirTse_-h02qZ6ctmBzw",
      "watch_key": "@trueman_project",
      "title": "trueman_project",
      "sticky_red_count": 8,
      "red_top_count": 7,
      "max_anomaly_ratio": 123.60140008921152
    }
  ]
}